ThesisHNSC/Model_Selection.py
ThesisHNSC/PredictionModule.py
ThesisHNSC/Validation.py
ThesisHNSC/__init__.py
ThesisHNSC/preprocessing.py
ThesisHNSC/hnscc/__init__.py
ThesisHNSC/hnscc/keras_metadata.pb
ThesisHNSC/hnscc/saved_model.pb
ThesisHNSC/hnscc/variables/variables.data-00000-of-00001
ThesisHNSC/hnscc/variables/variables.index
ThesisHNSC/hpv/__init__.py
ThesisHNSC/hpv/keras_metadata.pb
ThesisHNSC/hpv/saved_model.pb
ThesisHNSC/hpv/variables/variables.data-00000-of-00001
ThesisHNSC/hpv/variables/variables.index
ThesisHNSC-0.0.6.dist-info/METADATA
ThesisHNSC-0.0.6.dist-info/WHEEL
ThesisHNSC-0.0.6.dist-info/top_level.txt
ThesisHNSC-0.0.6.dist-info/RECORD
