Metadata-Version: 2.1
Name: ThesisHNSC
Version: 0.0.6
Summary: test file
Author: Akanksha
Author-email: <akanksha20331@iiitd.ac.in>
License: UNKNOWN
Keywords: python,Head and neck cancer,Diagnosis,Single cell,Genomics
Platform: UNKNOWN
Classifier: Development Status :: 1 - Planning
Classifier: Intended Audience :: Developers
Classifier: Programming Language :: Python :: 3
Classifier: Operating System :: Unix
Classifier: Operating System :: MacOS :: MacOS X
Classifier: Operating System :: Microsoft :: Windows
Requires-Dist: pandas
Requires-Dist: numpy
Requires-Dist: tensorflow
Requires-Dist: keras
